pymedsec/__init__.py
pymedsec/audit.py
pymedsec/cli.py
pymedsec/config.py
pymedsec/config_api.py
pymedsec/crypto.py
pymedsec/intake.py
pymedsec/public_api.py
pymedsec/sanitize.py
pymedsec/validate.py
pymedsec/blockchain/__init__.py
pymedsec/blockchain/base.py
pymedsec/blockchain/ethereum.py
pymedsec/blockchain/hyperledger.py
pymedsec/blockchain/mock.py
pymedsec/kms/__init__.py
pymedsec/kms/aws_kms.py
pymedsec/kms/base.py
pymedsec/kms/mock.py
pymedsec/kms/vault.py
pymedsec/policies/gdpr_default.yaml
pymedsec/policies/gxplab_default.yaml
pymedsec/policies/hipaa_default.yaml
pymedsec-0.1.0.dist-info/licenses/LICENSE
pymedsec-0.1.0.dist-info/licenses/NOTICE
pymedsec-0.1.0.dist-info/METADATA
pymedsec-0.1.0.dist-info/WHEEL
pymedsec-0.1.0.dist-info/entry_points.txt
pymedsec-0.1.0.dist-info/top_level.txt
pymedsec-0.1.0.dist-info/RECORD
