Metadata-Version: 2.4
Name: pymedsec
Version: 0.1.0
Summary: HIPAA/GDPR-ready medical image sanitization and encryption library with blockchain audit anchoring
Home-page: https://github.com/Faerque/pymedsec
Author: PyMedSec Contributors
Author-email: PyMedSec Contributors <opensource@pymedsec.org>
Maintainer: PyMedSec Development Team
Maintainer-email: PyMedSec Development Team <dev@pymedsec.org>
License: Apache-2.0
Project-URL: Homepage, https://github.com/Faerque/pymedsec
Project-URL: Documentation, https://pymedsec.readthedocs.io/
Project-URL: Repository, https://github.com/Faerque/pymedsec.git
Project-URL: Issues, https://github.com/Faerque/pymedsec/issues
Project-URL: Security, https://github.com/Faerque/pymedsec/security/policy
Project-URL: Changelog, https://github.com/Faerque/pymedsec/blob/main/CHANGELOG.md
Project-URL: Source Code, https://github.com/Faerque/pymedsec
Keywords: medical,imaging,security,hipaa,gdpr,encryption,dicom,blockchain
Classifier: Development Status :: 4 - Beta
Classifier: Intended Audience :: Healthcare Industry
Classifier: Intended Audience :: Developers
Classifier: License :: OSI Approved :: Apache Software License
Classifier: Programming Language :: Python :: 3
Classifier: Programming Language :: Python :: 3.8
Classifier: Programming Language :: Python :: 3.9
Classifier: Programming Language :: Python :: 3.10
Classifier: Programming Language :: Python :: 3.11
Classifier: Programming Language :: Python :: 3.12
Classifier: Topic :: Scientific/Engineering :: Medical Science Apps.
Classifier: Topic :: Security :: Cryptography
Classifier: Topic :: Software Development :: Libraries :: Python Modules
Classifier: Operating System :: OS Independent
Requires-Python: >=3.8
License-File: LICENSE
License-File: NOTICE
Requires-Dist: cryptography>=41.0.0
Requires-Dist: pydicom>=2.3.0
Requires-Dist: Pillow>=9.0.0
Requires-Dist: python-dateutil>=2.8.0
Requires-Dist: pyyaml>=6.0
Requires-Dist: click>=8.0.0
Requires-Dist: numpy>=1.20.0
Requires-Dist: importlib-resources>=5.0.0; python_version < "3.9"
Provides-Extra: dev
Requires-Dist: pytest>=7.0.0; extra == "dev"
Requires-Dist: pytest-cov>=4.0.0; extra == "dev"
Requires-Dist: black>=22.0.0; extra == "dev"
Requires-Dist: flake8>=5.0.0; extra == "dev"
Requires-Dist: build>=0.10.0; extra == "dev"
Requires-Dist: twine>=4.0.0; extra == "dev"
Requires-Dist: safety>=2.3.0; extra == "dev"
Requires-Dist: bandit[toml]>=1.7.0; extra == "dev"
Requires-Dist: pre-commit>=3.0.0; extra == "dev"
Provides-Extra: docs
Requires-Dist: sphinx>=7.0.0; extra == "docs"
Requires-Dist: sphinx-rtd-theme>=1.3.0; extra == "docs"
Requires-Dist: myst-parser>=2.0.0; extra == "docs"
Requires-Dist: sphinx-autodoc-typehints>=1.23.0; extra == "docs"
Requires-Dist: sphinx-copybutton>=0.5.0; extra == "docs"
Provides-Extra: test
Requires-Dist: pytest>=7.0.0; extra == "test"
Requires-Dist: pytest-cov>=4.0.0; extra == "test"
Provides-Extra: all
Requires-Dist: pytest>=7.0.0; extra == "all"
Requires-Dist: pytest-cov>=4.0.0; extra == "all"
Requires-Dist: pytesseract>=0.3.0; extra == "all"
Requires-Dist: boto3>=1.26.0; extra == "all"
Requires-Dist: hvac>=1.0.0; extra == "all"
Requires-Dist: web3>=6.0.0; extra == "all"
Provides-Extra: ocr
Requires-Dist: pytesseract>=0.3.0; extra == "ocr"
Provides-Extra: aws
Requires-Dist: boto3>=1.26.0; extra == "aws"
Provides-Extra: vault
Requires-Dist: hvac>=1.0.0; extra == "vault"
Provides-Extra: blockchain
Requires-Dist: web3>=6.0.0; extra == "blockchain"
Dynamic: license-file
